python_enigma_bar/__init__.py
python_enigma_bar/components.py
python_enigma_bar/config.py
python_enigma_bar/main.py
python_enigma_bar/tests.py
python_enigma_bar-0.0.3.dist-info/METADATA
python_enigma_bar-0.0.3.dist-info/WHEEL
python_enigma_bar-0.0.3.dist-info/top_level.txt
python_enigma_bar-0.0.3.dist-info/RECORD
