Metadata-Version: 2.1
Name: python-enigma-bar
Version: 0.0.3
Summary: Virtual Enigma Machine
Home-page: https://gitlab.com/arwindersngh62/python-enigma.git
Author: Arwinder Singh
Author-email: arwindersingh021@gmail.com
License: GNU GPLv3
Platform: UNKNOWN
